setup.py
jsonl/__init__.py
jsonl/jsonl.py
jsonl.egg-info/PKG-INFO
jsonl.egg-info/SOURCES.txt
jsonl.egg-info/dependency_links.txt
jsonl.egg-info/requires.txt
jsonl.egg-info/top_level.txt
jsonl.egg-info/zip-safe
test/testJsonl.py