Metadata-Version: 1.1
Name: jsonl
Version: 1.6
Summary: JSON decoding to mutable or immutable objects allowing attribute access
Home-page: https://bitbucket.org/sys-git/jsonl
Author: Francis Horsman
Author-email: francis.horsman@gmail.com
License: GNU General Public License
Platform: any
Classifier: Development Status :: 5 - Production/Stable
Classifier: Intended Audience :: Developers
Classifier: License :: OSI Approved :: GNU General Public License v3 (GPLv3)
Classifier: Operating System :: OS Independent
Classifier: Programming Language :: Python
Classifier: Topic :: Software Development :: Libraries :: Python Modules
